hyprshade/__init__.py
hyprshade/__main__.py
hyprshade/py.typed
hyprshade/utils.py
hyprshade/cli/__init__.py
hyprshade/cli/auto.py
hyprshade/cli/current.py
hyprshade/cli/install.py
hyprshade/cli/ls.py
hyprshade/cli/off.py
hyprshade/cli/on.py
hyprshade/cli/toggle.py
hyprshade/cli/utils.py
hyprshade/config/__init__.py
hyprshade/config/core.py
hyprshade/config/schedule.py
hyprshade/config/types.py
hyprshade/config/utils.py
hyprshade/shader/__init__.py
hyprshade/shader/core.py
hyprshade/shader/hyprctl.py
hyprshade-4.0.0.data/data/share/hyprshade/shaders/blue-light-filter.glsl
hyprshade-4.0.0.data/data/share/hyprshade/shaders/vibrance.glsl
hyprshade-4.0.0.dist-info/METADATA
hyprshade-4.0.0.dist-info/WHEEL
hyprshade-4.0.0.dist-info/entry_points.txt
hyprshade-4.0.0.dist-info/licenses/LICENSE
hyprshade-4.0.0.dist-info/RECORD
