Metadata-Version: 2.4
Name: hyprshade
Version: 4.0.0
Summary: Hyprland shade configuration tool
Project-URL: Issues, https://github.com/loqusion/hyprshade/issues
Project-URL: Source, https://github.com/loqusion/hyprshade
Author-email: John Bernard <loqusion@gmail.com>
License: MIT
License-File: LICENSE
Requires-Python: <4.0,>=3.11
Requires-Dist: click>=8.1.7
Requires-Dist: more-itertools>=10.1.0
